homeeasy/AsyncioHelper.py
homeeasy/CustomLogger.py
homeeasy/DeviceState.py
homeeasy/EncryptedMqtt.py
homeeasy/HomeEasyLib.py
homeeasy/HomeEasyLibLocal.py
homeeasy/HomeEasyLibLocalDiscovery.py
homeeasy/__init__.py
homeeasy/valueHelper.py
tests/__init__.py
tests/test_DeviceState.py
tests/test_EncryptedMqtt.py
tests/test_HomeEasyLib.py
homeeasy-0.0.8.dist-info/LICENSE
homeeasy-0.0.8.dist-info/METADATA
homeeasy-0.0.8.dist-info/WHEEL
homeeasy-0.0.8.dist-info/top_level.txt
homeeasy-0.0.8.dist-info/RECORD
