Metadata-Version: 2.1
Name: homeeasy
Version: 0.0.8
Summary: Control HVAC devices compatible with HomeEasy application.
Home-page: https://github.com/ki0ki0/homeeasylib
Author: Ihor Kostiuk
Author-email: igorkost@gmail.com
License: GPLv3
Platform: UNKNOWN
Classifier: Programming Language :: Python :: 3
Classifier: License :: OSI Approved :: GNU General Public License v3 (GPLv3)
Classifier: Operating System :: OS Independent
Classifier: Development Status :: 3 - Alpha
Classifier: Framework :: AsyncIO
Requires-Python: >=3.6
Requires-Dist: paho-mqtt
Requires-Dist: pycryptodome
